ZUMservices/__init__.py
ZUMservices/lib.py
zumservices_api_py-1.0.1.dist-info/LICENSE
zumservices_api_py-1.0.1.dist-info/METADATA
zumservices_api_py-1.0.1.dist-info/WHEEL
zumservices_api_py-1.0.1.dist-info/top_level.txt
zumservices_api_py-1.0.1.dist-info/RECORD
