Metadata-Version: 2.1
Name: zumservices-api-py
Version: 1.0.1
Summary: Python wrapper to interact with the ZUM Services API.
Home-page: https://github.com/zum-services/zumservices-api-py
Author: CodingRonin
Author-email: CodingRonin@zumcoin.org
License: UNKNOWN
Platform: UNKNOWN
Classifier: Programming Language :: Python :: 3
Classifier: License :: OSI Approved :: GNU Affero General Public License v3
